[
    {
        "soldier_formation_id": 101,
        "soldier_type_id_1": 202501,
        "soldier_proportion_1": 1,
        "soldier_type_id_2": "",
        "soldier_proportion_2": "",
        "soldier_type_id_3": "",
        "soldier_proportion_3": "",
        "soldier_type_id_4": "",
        "soldier_proportion_4": ""
    },
    {
        "soldier_formation_id": 102,
        "soldier_type_id_1": 202401,
        "soldier_proportion_1": 1,
        "soldier_type_id_2": "",
        "soldier_proportion_2": "",
        "soldier_type_id_3": "",
        "soldier_proportion_3": "",
        "soldier_type_id_4": "",
        "soldier_proportion_4": ""
    },
    {
        "soldier_formation_id": 103,
        "soldier_type_id_1": 202405,
        "soldier_proportion_1": 1,
        "soldier_type_id_2": "",
        "soldier_proportion_2": "",
        "soldier_type_id_3": "",
        "soldier_proportion_3": "",
        "soldier_type_id_4": "",
        "soldier_proportion_4": ""
    },
    {
        "soldier_formation_id": 104,
        "soldier_type_id_1": 202403,
        "soldier_proportion_1": 1,
        "soldier_type_id_2": "",
        "soldier_proportion_2": "",
        "soldier_type_id_3": "",
        "soldier_proportion_3": "",
        "soldier_type_id_4": "",
        "soldier_proportion_4": ""
    },
    {
        "soldier_formation_id": 105,
        "soldier_type_id_1": 202303,
        "soldier_proportion_1": 1,
        "soldier_type_id_2": "",
        "soldier_proportion_2": "",
        "soldier_type_id_3": "",
        "soldier_proportion_3": "",
        "soldier_type_id_4": "",
        "soldier_proportion_4": ""
    },
    {
        "soldier_formation_id": 106,
        "soldier_type_id_1": 202301,
        "soldier_proportion_1": 1,
        "soldier_type_id_2": "",
        "soldier_proportion_2": "",
        "soldier_type_id_3": "",
        "soldier_proportion_3": "",
        "soldier_type_id_4": "",
        "soldier_proportion_4": ""
    },
    {
        "soldier_formation_id": 107,
        "soldier_type_id_1": 202302,
        "soldier_proportion_1": 1,
        "soldier_type_id_2": "",
        "soldier_proportion_2": "",
        "soldier_type_id_3": "",
        "soldier_proportion_3": "",
        "soldier_type_id_4": "",
        "soldier_proportion_4": ""
    },
    {
        "soldier_formation_id": 108,
        "soldier_type_id_1": 202601,
        "soldier_proportion_1": 1,
        "soldier_type_id_2": "",
        "soldier_proportion_2": "",
        "soldier_type_id_3": "",
        "soldier_proportion_3": "",
        "soldier_type_id_4": "",
        "soldier_proportion_4": ""
    },
    {
        "soldier_formation_id": 109,
        "soldier_type_id_1": 202101,
        "soldier_proportion_1": 1,
        "soldier_type_id_2": "",
        "soldier_proportion_2": "",
        "soldier_type_id_3": "",
        "soldier_proportion_3": "",
        "soldier_type_id_4": "",
        "soldier_proportion_4": ""
    },
    {
        "soldier_formation_id": 110,
        "soldier_type_id_1": 202102,
        "soldier_proportion_1": 1,
        "soldier_type_id_2": "",
        "soldier_proportion_2": "",
        "soldier_type_id_3": "",
        "soldier_proportion_3": "",
        "soldier_type_id_4": "",
        "soldier_proportion_4": ""
    },
    {
        "soldier_formation_id": 111,
        "soldier_type_id_1": 202404,
        "soldier_proportion_1": 1,
        "soldier_type_id_2": "",
        "soldier_proportion_2": "",
        "soldier_type_id_3": "",
        "soldier_proportion_3": "",
        "soldier_type_id_4": "",
        "soldier_proportion_4": ""
    },
    {
        "soldier_formation_id": 112,
        "soldier_type_id_1": 202402,
        "soldier_proportion_1": 1,
        "soldier_type_id_2": "",
        "soldier_proportion_2": "",
        "soldier_type_id_3": "",
        "soldier_proportion_3": "",
        "soldier_type_id_4": "",
        "soldier_proportion_4": ""
    },
    {
        "soldier_formation_id": 113,
        "soldier_type_id_1": 202502,
        "soldier_proportion_1": 1,
        "soldier_type_id_2": 202405,
        "soldier_proportion_2": 2,
        "soldier_type_id_3": "",
        "soldier_proportion_3": "",
        "soldier_type_id_4": "",
        "soldier_proportion_4": ""
    },
    {
        "soldier_formation_id": 114,
        "soldier_type_id_1": 202502,
        "soldier_proportion_1": 1,
        "soldier_type_id_2": 202303,
        "soldier_proportion_2": 2,
        "soldier_type_id_3": "",
        "soldier_proportion_3": "",
        "soldier_type_id_4": "",
        "soldier_proportion_4": ""
    },
    {
        "soldier_formation_id": 115,
        "soldier_type_id_1": 202502,
        "soldier_proportion_1": 1,
        "soldier_type_id_2": 202301,
        "soldier_proportion_2": 2,
        "soldier_type_id_3": "",
        "soldier_proportion_3": "",
        "soldier_type_id_4": "",
        "soldier_proportion_4": ""
    },
    {
        "soldier_formation_id": 116,
        "soldier_type_id_1": 202502,
        "soldier_proportion_1": 1,
        "soldier_type_id_2": 202302,
        "soldier_proportion_2": 2,
        "soldier_type_id_3": "",
        "soldier_proportion_3": "",
        "soldier_type_id_4": "",
        "soldier_proportion_4": ""
    },
    {
        "soldier_formation_id": 117,
        "soldier_type_id_1": 202501,
        "soldier_proportion_1": 1,
        "soldier_type_id_2": 202405,
        "soldier_proportion_2": 2,
        "soldier_type_id_3": "",
        "soldier_proportion_3": "",
        "soldier_type_id_4": "",
        "soldier_proportion_4": ""
    },
    {
        "soldier_formation_id": 118,
        "soldier_type_id_1": 202501,
        "soldier_proportion_1": 1,
        "soldier_type_id_2": 202303,
        "soldier_proportion_2": 2,
        "soldier_type_id_3": "",
        "soldier_proportion_3": "",
        "soldier_type_id_4": "",
        "soldier_proportion_4": ""
    },
    {
        "soldier_formation_id": 119,
        "soldier_type_id_1": 202501,
        "soldier_proportion_1": 1,
        "soldier_type_id_2": 202301,
        "soldier_proportion_2": 2,
        "soldier_type_id_3": "",
        "soldier_proportion_3": "",
        "soldier_type_id_4": "",
        "soldier_proportion_4": ""
    },
    {
        "soldier_formation_id": 120,
        "soldier_type_id_1": 202501,
        "soldier_proportion_1": 1,
        "soldier_type_id_2": 202302,
        "soldier_proportion_2": 2,
        "soldier_type_id_3": "",
        "soldier_proportion_3": "",
        "soldier_type_id_4": "",
        "soldier_proportion_4": ""
    },
    {
        "soldier_formation_id": 121,
        "soldier_type_id_1": 202501,
        "soldier_proportion_1": 1,
        "soldier_type_id_2": 202401,
        "soldier_proportion_2": 2,
        "soldier_type_id_3": "",
        "soldier_proportion_3": "",
        "soldier_type_id_4": "",
        "soldier_proportion_4": ""
    },
    {
        "soldier_formation_id": 122,
        "soldier_type_id_1": 202405,
        "soldier_proportion_1": 1,
        "soldier_type_id_2": 202403,
        "soldier_proportion_2": 1,
        "soldier_type_id_3": "",
        "soldier_proportion_3": "",
        "soldier_type_id_4": "",
        "soldier_proportion_4": ""
    },
    {
        "soldier_formation_id": 123,
        "soldier_type_id_1": 202405,
        "soldier_proportion_1": 1,
        "soldier_type_id_2": 202601,
        "soldier_proportion_2": 1,
        "soldier_type_id_3": "",
        "soldier_proportion_3": "",
        "soldier_type_id_4": "",
        "soldier_proportion_4": ""
    },
    {
        "soldier_formation_id": 124,
        "soldier_type_id_1": 202405,
        "soldier_proportion_1": 1,
        "soldier_type_id_2": 202101,
        "soldier_proportion_2": 1,
        "soldier_type_id_3": "",
        "soldier_proportion_3": "",
        "soldier_type_id_4": "",
        "soldier_proportion_4": ""
    },
    {
        "soldier_formation_id": 125,
        "soldier_type_id_1": 202405,
        "soldier_proportion_1": 1,
        "soldier_type_id_2": 202301,
        "soldier_proportion_2": 1,
        "soldier_type_id_3": "",
        "soldier_proportion_3": "",
        "soldier_type_id_4": "",
        "soldier_proportion_4": ""
    },
    {
        "soldier_formation_id": 126,
        "soldier_type_id_1": 202405,
        "soldier_proportion_1": 1,
        "soldier_type_id_2": 202302,
        "soldier_proportion_2": 1,
        "soldier_type_id_3": "",
        "soldier_proportion_3": "",
        "soldier_type_id_4": "",
        "soldier_proportion_4": ""
    },
    {
        "soldier_formation_id": 127,
        "soldier_type_id_1": 202405,
        "soldier_proportion_1": 1,
        "soldier_type_id_2": 202303,
        "soldier_proportion_2": 1,
        "soldier_type_id_3": "",
        "soldier_proportion_3": "",
        "soldier_type_id_4": "",
        "soldier_proportion_4": ""
    },
    {
        "soldier_formation_id": 128,
        "soldier_type_id_1": 202301,
        "soldier_proportion_1": 1,
        "soldier_type_id_2": 202302,
        "soldier_proportion_2": 1,
        "soldier_type_id_3": "",
        "soldier_proportion_3": "",
        "soldier_type_id_4": "",
        "soldier_proportion_4": ""
    },
    {
        "soldier_formation_id": 129,
        "soldier_type_id_1": 202303,
        "soldier_proportion_1": 1,
        "soldier_type_id_2": 202401,
        "soldier_proportion_2": 1,
        "soldier_type_id_3": "",
        "soldier_proportion_3": "",
        "soldier_type_id_4": "",
        "soldier_proportion_4": ""
    },
    {
        "soldier_formation_id": 130,
        "soldier_type_id_1": 202303,
        "soldier_proportion_1": 1,
        "soldier_type_id_2": 202301,
        "soldier_proportion_2": 1,
        "soldier_type_id_3": "",
        "soldier_proportion_3": "",
        "soldier_type_id_4": "",
        "soldier_proportion_4": ""
    },
    {
        "soldier_formation_id": 131,
        "soldier_type_id_1": 202303,
        "soldier_proportion_1": 1,
        "soldier_type_id_2": 202302,
        "soldier_proportion_2": 1,
        "soldier_type_id_3": "",
        "soldier_proportion_3": "",
        "soldier_type_id_4": "",
        "soldier_proportion_4": ""
    },
    {
        "soldier_formation_id": 132,
        "soldier_type_id_1": 202403,
        "soldier_proportion_1": 1,
        "soldier_type_id_2": 202301,
        "soldier_proportion_2": 1,
        "soldier_type_id_3": "",
        "soldier_proportion_3": "",
        "soldier_type_id_4": "",
        "soldier_proportion_4": ""
    },
    {
        "soldier_formation_id": 133,
        "soldier_type_id_1": 202403,
        "soldier_proportion_1": 1,
        "soldier_type_id_2": 202302,
        "soldier_proportion_2": 1,
        "soldier_type_id_3": "",
        "soldier_proportion_3": "",
        "soldier_type_id_4": "",
        "soldier_proportion_4": ""
    },
    {
        "soldier_formation_id": 134,
        "soldier_type_id_1": 202403,
        "soldier_proportion_1": 1,
        "soldier_type_id_2": 202303,
        "soldier_proportion_2": 1,
        "soldier_type_id_3": "",
        "soldier_proportion_3": "",
        "soldier_type_id_4": "",
        "soldier_proportion_4": ""
    },
    {
        "soldier_formation_id": 135,
        "soldier_type_id_1": 202502,
        "soldier_proportion_1": 2,
        "soldier_type_id_2": 202405,
        "soldier_proportion_2": 2,
        "soldier_type_id_3": 202301,
        "soldier_proportion_3": 1,
        "soldier_type_id_4": "",
        "soldier_proportion_4": ""
    },
    {
        "soldier_formation_id": 136,
        "soldier_type_id_1": 202502,
        "soldier_proportion_1": 2,
        "soldier_type_id_2": 202405,
        "soldier_proportion_2": 2,
        "soldier_type_id_3": 202302,
        "soldier_proportion_3": 1,
        "soldier_type_id_4": "",
        "soldier_proportion_4": ""
    },
    {
        "soldier_formation_id": 137,
        "soldier_type_id_1": 202502,
        "soldier_proportion_1": 2,
        "soldier_type_id_2": 202405,
        "soldier_proportion_2": 2,
        "soldier_type_id_3": 202303,
        "soldier_proportion_3": 1,
        "soldier_type_id_4": "",
        "soldier_proportion_4": ""
    },
    {
        "soldier_formation_id": 138,
        "soldier_type_id_1": 202502,
        "soldier_proportion_1": 2,
        "soldier_type_id_2": 202401,
        "soldier_proportion_2": 2,
        "soldier_type_id_3": 202301,
        "soldier_proportion_3": 1,
        "soldier_type_id_4": "",
        "soldier_proportion_4": ""
    },
    {
        "soldier_formation_id": 139,
        "soldier_type_id_1": 202502,
        "soldier_proportion_1": 2,
        "soldier_type_id_2": 202401,
        "soldier_proportion_2": 2,
        "soldier_type_id_3": 202302,
        "soldier_proportion_3": 1,
        "soldier_type_id_4": "",
        "soldier_proportion_4": ""
    },
    {
        "soldier_formation_id": 140,
        "soldier_type_id_1": 202502,
        "soldier_proportion_1": 2,
        "soldier_type_id_2": 202401,
        "soldier_proportion_2": 2,
        "soldier_type_id_3": 202303,
        "soldier_proportion_3": 1,
        "soldier_type_id_4": "",
        "soldier_proportion_4": ""
    },
    {
        "soldier_formation_id": 141,
        "soldier_type_id_1": 202502,
        "soldier_proportion_1": 2,
        "soldier_type_id_2": 202403,
        "soldier_proportion_2": 2,
        "soldier_type_id_3": 202301,
        "soldier_proportion_3": 1,
        "soldier_type_id_4": "",
        "soldier_proportion_4": ""
    },
    {
        "soldier_formation_id": 142,
        "soldier_type_id_1": 202502,
        "soldier_proportion_1": 2,
        "soldier_type_id_2": 202403,
        "soldier_proportion_2": 2,
        "soldier_type_id_3": 202302,
        "soldier_proportion_3": 1,
        "soldier_type_id_4": "",
        "soldier_proportion_4": ""
    },
    {
        "soldier_formation_id": 143,
        "soldier_type_id_1": 202502,
        "soldier_proportion_1": 2,
        "soldier_type_id_2": 202403,
        "soldier_proportion_2": 2,
        "soldier_type_id_3": 202303,
        "soldier_proportion_3": 1,
        "soldier_type_id_4": "",
        "soldier_proportion_4": ""
    },
    {
        "soldier_formation_id": 144,
        "soldier_type_id_1": 202501,
        "soldier_proportion_1": 2,
        "soldier_type_id_2": 202405,
        "soldier_proportion_2": 2,
        "soldier_type_id_3": 202301,
        "soldier_proportion_3": 1,
        "soldier_type_id_4": "",
        "soldier_proportion_4": ""
    },
    {
        "soldier_formation_id": 145,
        "soldier_type_id_1": 202501,
        "soldier_proportion_1": 2,
        "soldier_type_id_2": 202405,
        "soldier_proportion_2": 2,
        "soldier_type_id_3": 202302,
        "soldier_proportion_3": 1,
        "soldier_type_id_4": "",
        "soldier_proportion_4": ""
    },
    {
        "soldier_formation_id": 146,
        "soldier_type_id_1": 202501,
        "soldier_proportion_1": 2,
        "soldier_type_id_2": 202405,
        "soldier_proportion_2": 2,
        "soldier_type_id_3": 202303,
        "soldier_proportion_3": 1,
        "soldier_type_id_4": "",
        "soldier_proportion_4": ""
    },
    {
        "soldier_formation_id": 147,
        "soldier_type_id_1": 202501,
        "soldier_proportion_1": 2,
        "soldier_type_id_2": 202401,
        "soldier_proportion_2": 2,
        "soldier_type_id_3": 202301,
        "soldier_proportion_3": 1,
        "soldier_type_id_4": "",
        "soldier_proportion_4": ""
    },
    {
        "soldier_formation_id": 148,
        "soldier_type_id_1": 202501,
        "soldier_proportion_1": 2,
        "soldier_type_id_2": 202401,
        "soldier_proportion_2": 2,
        "soldier_type_id_3": 202302,
        "soldier_proportion_3": 1,
        "soldier_type_id_4": "",
        "soldier_proportion_4": ""
    },
    {
        "soldier_formation_id": 149,
        "soldier_type_id_1": 202501,
        "soldier_proportion_1": 2,
        "soldier_type_id_2": 202401,
        "soldier_proportion_2": 2,
        "soldier_type_id_3": 202303,
        "soldier_proportion_3": 1,
        "soldier_type_id_4": "",
        "soldier_proportion_4": ""
    },
    {
        "soldier_formation_id": 150,
        "soldier_type_id_1": 202501,
        "soldier_proportion_1": 2,
        "soldier_type_id_2": 202403,
        "soldier_proportion_2": 2,
        "soldier_type_id_3": 202301,
        "soldier_proportion_3": 1,
        "soldier_type_id_4": "",
        "soldier_proportion_4": ""
    },
    {
        "soldier_formation_id": 151,
        "soldier_type_id_1": 202501,
        "soldier_proportion_1": 2,
        "soldier_type_id_2": 202403,
        "soldier_proportion_2": 2,
        "soldier_type_id_3": 202302,
        "soldier_proportion_3": 1,
        "soldier_type_id_4": "",
        "soldier_proportion_4": ""
    },
    {
        "soldier_formation_id": 152,
        "soldier_type_id_1": 202501,
        "soldier_proportion_1": 2,
        "soldier_type_id_2": 202403,
        "soldier_proportion_2": 2,
        "soldier_type_id_3": 202303,
        "soldier_proportion_3": 1,
        "soldier_type_id_4": "",
        "soldier_proportion_4": ""
    },
    {
        "soldier_formation_id": 153,
        "soldier_type_id_1": 202601,
        "soldier_proportion_1": 2,
        "soldier_type_id_2": 202405,
        "soldier_proportion_2": 2,
        "soldier_type_id_3": 202301,
        "soldier_proportion_3": 1,
        "soldier_type_id_4": "",
        "soldier_proportion_4": ""
    },
    {
        "soldier_formation_id": 154,
        "soldier_type_id_1": 202601,
        "soldier_proportion_1": 2,
        "soldier_type_id_2": 202405,
        "soldier_proportion_2": 2,
        "soldier_type_id_3": 202302,
        "soldier_proportion_3": 1,
        "soldier_type_id_4": "",
        "soldier_proportion_4": ""
    },
    {
        "soldier_formation_id": 155,
        "soldier_type_id_1": 202601,
        "soldier_proportion_1": 2,
        "soldier_type_id_2": 202405,
        "soldier_proportion_2": 2,
        "soldier_type_id_3": 202303,
        "soldier_proportion_3": 1,
        "soldier_type_id_4": "",
        "soldier_proportion_4": ""
    },
    {
        "soldier_formation_id": 156,
        "soldier_type_id_1": 202601,
        "soldier_proportion_1": 2,
        "soldier_type_id_2": 202401,
        "soldier_proportion_2": 2,
        "soldier_type_id_3": 202301,
        "soldier_proportion_3": 1,
        "soldier_type_id_4": "",
        "soldier_proportion_4": ""
    },
    {
        "soldier_formation_id": 157,
        "soldier_type_id_1": 202601,
        "soldier_proportion_1": 2,
        "soldier_type_id_2": 202401,
        "soldier_proportion_2": 2,
        "soldier_type_id_3": 202302,
        "soldier_proportion_3": 1,
        "soldier_type_id_4": "",
        "soldier_proportion_4": ""
    },
    {
        "soldier_formation_id": 158,
        "soldier_type_id_1": 202601,
        "soldier_proportion_1": 2,
        "soldier_type_id_2": 202401,
        "soldier_proportion_2": 2,
        "soldier_type_id_3": 202303,
        "soldier_proportion_3": 1,
        "soldier_type_id_4": "",
        "soldier_proportion_4": ""
    },
    {
        "soldier_formation_id": 159,
        "soldier_type_id_1": 202601,
        "soldier_proportion_1": 2,
        "soldier_type_id_2": 202403,
        "soldier_proportion_2": 2,
        "soldier_type_id_3": 202301,
        "soldier_proportion_3": 1,
        "soldier_type_id_4": "",
        "soldier_proportion_4": ""
    },
    {
        "soldier_formation_id": 160,
        "soldier_type_id_1": 202601,
        "soldier_proportion_1": 2,
        "soldier_type_id_2": 202403,
        "soldier_proportion_2": 2,
        "soldier_type_id_3": 202302,
        "soldier_proportion_3": 1,
        "soldier_type_id_4": "",
        "soldier_proportion_4": ""
    },
    {
        "soldier_formation_id": 161,
        "soldier_type_id_1": 202601,
        "soldier_proportion_1": 2,
        "soldier_type_id_2": 202403,
        "soldier_proportion_2": 2,
        "soldier_type_id_3": 202303,
        "soldier_proportion_3": 1,
        "soldier_type_id_4": "",
        "soldier_proportion_4": ""
    },
    {
        "soldier_formation_id": 162,
        "soldier_type_id_1": 202101,
        "soldier_proportion_1": 2,
        "soldier_type_id_2": 202405,
        "soldier_proportion_2": 2,
        "soldier_type_id_3": 202301,
        "soldier_proportion_3": 1,
        "soldier_type_id_4": "",
        "soldier_proportion_4": ""
    },
    {
        "soldier_formation_id": 163,
        "soldier_type_id_1": 202101,
        "soldier_proportion_1": 2,
        "soldier_type_id_2": 202405,
        "soldier_proportion_2": 2,
        "soldier_type_id_3": 202302,
        "soldier_proportion_3": 1,
        "soldier_type_id_4": "",
        "soldier_proportion_4": ""
    },
    {
        "soldier_formation_id": 164,
        "soldier_type_id_1": 202101,
        "soldier_proportion_1": 2,
        "soldier_type_id_2": 202405,
        "soldier_proportion_2": 2,
        "soldier_type_id_3": 202303,
        "soldier_proportion_3": 1,
        "soldier_type_id_4": "",
        "soldier_proportion_4": ""
    },
    {
        "soldier_formation_id": 165,
        "soldier_type_id_1": 202101,
        "soldier_proportion_1": 2,
        "soldier_type_id_2": 202401,
        "soldier_proportion_2": 2,
        "soldier_type_id_3": 202301,
        "soldier_proportion_3": 1,
        "soldier_type_id_4": "",
        "soldier_proportion_4": ""
    },
    {
        "soldier_formation_id": 166,
        "soldier_type_id_1": 202101,
        "soldier_proportion_1": 2,
        "soldier_type_id_2": 202401,
        "soldier_proportion_2": 2,
        "soldier_type_id_3": 202302,
        "soldier_proportion_3": 1,
        "soldier_type_id_4": "",
        "soldier_proportion_4": ""
    },
    {
        "soldier_formation_id": 167,
        "soldier_type_id_1": 202101,
        "soldier_proportion_1": 2,
        "soldier_type_id_2": 202401,
        "soldier_proportion_2": 2,
        "soldier_type_id_3": 202303,
        "soldier_proportion_3": 1,
        "soldier_type_id_4": "",
        "soldier_proportion_4": ""
    },
    {
        "soldier_formation_id": 168,
        "soldier_type_id_1": 202101,
        "soldier_proportion_1": 2,
        "soldier_type_id_2": 202403,
        "soldier_proportion_2": 2,
        "soldier_type_id_3": 202301,
        "soldier_proportion_3": 1,
        "soldier_type_id_4": "",
        "soldier_proportion_4": ""
    },
    {
        "soldier_formation_id": 169,
        "soldier_type_id_1": 202101,
        "soldier_proportion_1": 2,
        "soldier_type_id_2": 202403,
        "soldier_proportion_2": 2,
        "soldier_type_id_3": 202302,
        "soldier_proportion_3": 1,
        "soldier_type_id_4": "",
        "soldier_proportion_4": ""
    },
    {
        "soldier_formation_id": 170,
        "soldier_type_id_1": 202101,
        "soldier_proportion_1": 2,
        "soldier_type_id_2": 202403,
        "soldier_proportion_2": 2,
        "soldier_type_id_3": 202303,
        "soldier_proportion_3": 1,
        "soldier_type_id_4": "",
        "soldier_proportion_4": ""
    },
    {
        "soldier_formation_id": 171,
        "soldier_type_id_1": 202102,
        "soldier_proportion_1": 2,
        "soldier_type_id_2": 202405,
        "soldier_proportion_2": 2,
        "soldier_type_id_3": 202301,
        "soldier_proportion_3": 1,
        "soldier_type_id_4": "",
        "soldier_proportion_4": ""
    },
    {
        "soldier_formation_id": 172,
        "soldier_type_id_1": 202102,
        "soldier_proportion_1": 2,
        "soldier_type_id_2": 202405,
        "soldier_proportion_2": 2,
        "soldier_type_id_3": 202302,
        "soldier_proportion_3": 1,
        "soldier_type_id_4": "",
        "soldier_proportion_4": ""
    },
    {
        "soldier_formation_id": 173,
        "soldier_type_id_1": 202102,
        "soldier_proportion_1": 2,
        "soldier_type_id_2": 202405,
        "soldier_proportion_2": 2,
        "soldier_type_id_3": 202303,
        "soldier_proportion_3": 1,
        "soldier_type_id_4": "",
        "soldier_proportion_4": ""
    },
    {
        "soldier_formation_id": 174,
        "soldier_type_id_1": 202102,
        "soldier_proportion_1": 2,
        "soldier_type_id_2": 202401,
        "soldier_proportion_2": 2,
        "soldier_type_id_3": 202301,
        "soldier_proportion_3": 1,
        "soldier_type_id_4": "",
        "soldier_proportion_4": ""
    },
    {
        "soldier_formation_id": 175,
        "soldier_type_id_1": 202102,
        "soldier_proportion_1": 2,
        "soldier_type_id_2": 202401,
        "soldier_proportion_2": 2,
        "soldier_type_id_3": 202302,
        "soldier_proportion_3": 1,
        "soldier_type_id_4": "",
        "soldier_proportion_4": ""
    },
    {
        "soldier_formation_id": 176,
        "soldier_type_id_1": 202102,
        "soldier_proportion_1": 2,
        "soldier_type_id_2": 202401,
        "soldier_proportion_2": 2,
        "soldier_type_id_3": 202303,
        "soldier_proportion_3": 1,
        "soldier_type_id_4": "",
        "soldier_proportion_4": ""
    },
    {
        "soldier_formation_id": 177,
        "soldier_type_id_1": 202102,
        "soldier_proportion_1": 2,
        "soldier_type_id_2": 202403,
        "soldier_proportion_2": 2,
        "soldier_type_id_3": 202301,
        "soldier_proportion_3": 1,
        "soldier_type_id_4": "",
        "soldier_proportion_4": ""
    },
    {
        "soldier_formation_id": 178,
        "soldier_type_id_1": 202102,
        "soldier_proportion_1": 2,
        "soldier_type_id_2": 202403,
        "soldier_proportion_2": 2,
        "soldier_type_id_3": 202302,
        "soldier_proportion_3": 1,
        "soldier_type_id_4": "",
        "soldier_proportion_4": ""
    },
    {
        "soldier_formation_id": 179,
        "soldier_type_id_1": 202102,
        "soldier_proportion_1": 2,
        "soldier_type_id_2": 202403,
        "soldier_proportion_2": 2,
        "soldier_type_id_3": 202303,
        "soldier_proportion_3": 1,
        "soldier_type_id_4": "",
        "soldier_proportion_4": ""
    },
    {
        "soldier_formation_id": 180,
        "soldier_type_id_1": 202701,
        "soldier_proportion_1": 1,
        "soldier_type_id_2": "",
        "soldier_proportion_2": "",
        "soldier_type_id_3": "",
        "soldier_proportion_3": "",
        "soldier_type_id_4": "",
        "soldier_proportion_4": ""
    },
    {
        "soldier_formation_id": 181,
        "soldier_type_id_1": 202702,
        "soldier_proportion_1": 1,
        "soldier_type_id_2": "",
        "soldier_proportion_2": "",
        "soldier_type_id_3": "",
        "soldier_proportion_3": "",
        "soldier_type_id_4": "",
        "soldier_proportion_4": ""
    },
    {
        "soldier_formation_id": 182,
        "soldier_type_id_1": 202703,
        "soldier_proportion_1": 1,
        "soldier_type_id_2": "",
        "soldier_proportion_2": "",
        "soldier_type_id_3": "",
        "soldier_proportion_3": "",
        "soldier_type_id_4": "",
        "soldier_proportion_4": ""
    },
    {
        "soldier_formation_id": 183,
        "soldier_type_id_1": 202704,
        "soldier_proportion_1": 1,
        "soldier_type_id_2": "",
        "soldier_proportion_2": "",
        "soldier_type_id_3": "",
        "soldier_proportion_3": "",
        "soldier_type_id_4": "",
        "soldier_proportion_4": ""
    },
    {
        "soldier_formation_id": 184,
        "soldier_type_id_1": 202404,
        "soldier_proportion_1": 1,
        "soldier_type_id_2": "",
        "soldier_proportion_2": "",
        "soldier_type_id_3": "",
        "soldier_proportion_3": "",
        "soldier_type_id_4": "",
        "soldier_proportion_4": ""
    },
    {
        "soldier_formation_id": 185,
        "soldier_type_id_1": 202502,
        "soldier_proportion_1": 2,
        "soldier_type_id_2": 202405,
        "soldier_proportion_2": 2,
        "soldier_type_id_3": 202301,
        "soldier_proportion_3": 1,
        "soldier_type_id_4": 202701,
        "soldier_proportion_4": 1
    },
    {
        "soldier_formation_id": 186,
        "soldier_type_id_1": 202502,
        "soldier_proportion_1": 2,
        "soldier_type_id_2": 202405,
        "soldier_proportion_2": 2,
        "soldier_type_id_3": 202302,
        "soldier_proportion_3": 1,
        "soldier_type_id_4": 202702,
        "soldier_proportion_4": 1
    },
    {
        "soldier_formation_id": 187,
        "soldier_type_id_1": 202502,
        "soldier_proportion_1": 2,
        "soldier_type_id_2": 202405,
        "soldier_proportion_2": 2,
        "soldier_type_id_3": 202303,
        "soldier_proportion_3": 1,
        "soldier_type_id_4": 202703,
        "soldier_proportion_4": 1
    },
    {
        "soldier_formation_id": 188,
        "soldier_type_id_1": 202502,
        "soldier_proportion_1": 2,
        "soldier_type_id_2": 202401,
        "soldier_proportion_2": 2,
        "soldier_type_id_3": 202301,
        "soldier_proportion_3": 1,
        "soldier_type_id_4": 202704,
        "soldier_proportion_4": 1
    },
    {
        "soldier_formation_id": 189,
        "soldier_type_id_1": 202502,
        "soldier_proportion_1": 2,
        "soldier_type_id_2": 202401,
        "soldier_proportion_2": 2,
        "soldier_type_id_3": 202302,
        "soldier_proportion_3": 1,
        "soldier_type_id_4": 202404,
        "soldier_proportion_4": 1
    },
    {
        "soldier_formation_id": 190,
        "soldier_type_id_1": 202502,
        "soldier_proportion_1": 2,
        "soldier_type_id_2": 202401,
        "soldier_proportion_2": 2,
        "soldier_type_id_3": 202303,
        "soldier_proportion_3": 1,
        "soldier_type_id_4": 202701,
        "soldier_proportion_4": 1
    },
    {
        "soldier_formation_id": 191,
        "soldier_type_id_1": 202502,
        "soldier_proportion_1": 2,
        "soldier_type_id_2": 202403,
        "soldier_proportion_2": 2,
        "soldier_type_id_3": 202301,
        "soldier_proportion_3": 1,
        "soldier_type_id_4": 202702,
        "soldier_proportion_4": 1
    },
    {
        "soldier_formation_id": 192,
        "soldier_type_id_1": 202502,
        "soldier_proportion_1": 2,
        "soldier_type_id_2": 202403,
        "soldier_proportion_2": 2,
        "soldier_type_id_3": 202302,
        "soldier_proportion_3": 1,
        "soldier_type_id_4": 202703,
        "soldier_proportion_4": 1
    },
    {
        "soldier_formation_id": 193,
        "soldier_type_id_1": 202502,
        "soldier_proportion_1": 2,
        "soldier_type_id_2": 202403,
        "soldier_proportion_2": 2,
        "soldier_type_id_3": 202303,
        "soldier_proportion_3": 1,
        "soldier_type_id_4": 202704,
        "soldier_proportion_4": 1
    },
    {
        "soldier_formation_id": 194,
        "soldier_type_id_1": 202501,
        "soldier_proportion_1": 2,
        "soldier_type_id_2": 202405,
        "soldier_proportion_2": 2,
        "soldier_type_id_3": 202301,
        "soldier_proportion_3": 1,
        "soldier_type_id_4": 202404,
        "soldier_proportion_4": 1
    },
    {
        "soldier_formation_id": 195,
        "soldier_type_id_1": 202501,
        "soldier_proportion_1": 2,
        "soldier_type_id_2": 202405,
        "soldier_proportion_2": 2,
        "soldier_type_id_3": 202302,
        "soldier_proportion_3": 1,
        "soldier_type_id_4": 202701,
        "soldier_proportion_4": 1
    },
    {
        "soldier_formation_id": 196,
        "soldier_type_id_1": 202501,
        "soldier_proportion_1": 2,
        "soldier_type_id_2": 202405,
        "soldier_proportion_2": 2,
        "soldier_type_id_3": 202303,
        "soldier_proportion_3": 1,
        "soldier_type_id_4": 202702,
        "soldier_proportion_4": 1
    },
    {
        "soldier_formation_id": 197,
        "soldier_type_id_1": 202501,
        "soldier_proportion_1": 2,
        "soldier_type_id_2": 202401,
        "soldier_proportion_2": 2,
        "soldier_type_id_3": 202301,
        "soldier_proportion_3": 1,
        "soldier_type_id_4": 202703,
        "soldier_proportion_4": 1
    },
    {
        "soldier_formation_id": 198,
        "soldier_type_id_1": 202501,
        "soldier_proportion_1": 2,
        "soldier_type_id_2": 202401,
        "soldier_proportion_2": 2,
        "soldier_type_id_3": 202302,
        "soldier_proportion_3": 1,
        "soldier_type_id_4": 202704,
        "soldier_proportion_4": 1
    },
    {
        "soldier_formation_id": 199,
        "soldier_type_id_1": 202501,
        "soldier_proportion_1": 2,
        "soldier_type_id_2": 202401,
        "soldier_proportion_2": 2,
        "soldier_type_id_3": 202303,
        "soldier_proportion_3": 1,
        "soldier_type_id_4": 202404,
        "soldier_proportion_4": 1
    },
    {
        "soldier_formation_id": 200,
        "soldier_type_id_1": 202501,
        "soldier_proportion_1": 2,
        "soldier_type_id_2": 202403,
        "soldier_proportion_2": 2,
        "soldier_type_id_3": 202301,
        "soldier_proportion_3": 1,
        "soldier_type_id_4": 202701,
        "soldier_proportion_4": 1
    },
    {
        "soldier_formation_id": 201,
        "soldier_type_id_1": 202501,
        "soldier_proportion_1": 2,
        "soldier_type_id_2": 202403,
        "soldier_proportion_2": 2,
        "soldier_type_id_3": 202302,
        "soldier_proportion_3": 1,
        "soldier_type_id_4": 202702,
        "soldier_proportion_4": 1
    },
    {
        "soldier_formation_id": 202,
        "soldier_type_id_1": 202501,
        "soldier_proportion_1": 2,
        "soldier_type_id_2": 202403,
        "soldier_proportion_2": 2,
        "soldier_type_id_3": 202303,
        "soldier_proportion_3": 1,
        "soldier_type_id_4": 202703,
        "soldier_proportion_4": 1
    },
    {
        "soldier_formation_id": 203,
        "soldier_type_id_1": 202601,
        "soldier_proportion_1": 2,
        "soldier_type_id_2": 202405,
        "soldier_proportion_2": 2,
        "soldier_type_id_3": 202301,
        "soldier_proportion_3": 1,
        "soldier_type_id_4": 202704,
        "soldier_proportion_4": 1
    },
    {
        "soldier_formation_id": 204,
        "soldier_type_id_1": 202601,
        "soldier_proportion_1": 2,
        "soldier_type_id_2": 202405,
        "soldier_proportion_2": 2,
        "soldier_type_id_3": 202302,
        "soldier_proportion_3": 1,
        "soldier_type_id_4": 202404,
        "soldier_proportion_4": 1
    },
    {
        "soldier_formation_id": 205,
        "soldier_type_id_1": 202601,
        "soldier_proportion_1": 2,
        "soldier_type_id_2": 202405,
        "soldier_proportion_2": 2,
        "soldier_type_id_3": 202303,
        "soldier_proportion_3": 1,
        "soldier_type_id_4": 202701,
        "soldier_proportion_4": 1
    },
    {
        "soldier_formation_id": 206,
        "soldier_type_id_1": 202601,
        "soldier_proportion_1": 2,
        "soldier_type_id_2": 202401,
        "soldier_proportion_2": 2,
        "soldier_type_id_3": 202301,
        "soldier_proportion_3": 1,
        "soldier_type_id_4": 202702,
        "soldier_proportion_4": 1
    },
    {
        "soldier_formation_id": 207,
        "soldier_type_id_1": 202601,
        "soldier_proportion_1": 2,
        "soldier_type_id_2": 202401,
        "soldier_proportion_2": 2,
        "soldier_type_id_3": 202302,
        "soldier_proportion_3": 1,
        "soldier_type_id_4": 202703,
        "soldier_proportion_4": 1
    },
    {
        "soldier_formation_id": 208,
        "soldier_type_id_1": 202601,
        "soldier_proportion_1": 2,
        "soldier_type_id_2": 202401,
        "soldier_proportion_2": 2,
        "soldier_type_id_3": 202303,
        "soldier_proportion_3": 1,
        "soldier_type_id_4": 202704,
        "soldier_proportion_4": 1
    },
    {
        "soldier_formation_id": 209,
        "soldier_type_id_1": 202601,
        "soldier_proportion_1": 2,
        "soldier_type_id_2": 202403,
        "soldier_proportion_2": 2,
        "soldier_type_id_3": 202301,
        "soldier_proportion_3": 1,
        "soldier_type_id_4": 202404,
        "soldier_proportion_4": 1
    },
    {
        "soldier_formation_id": 210,
        "soldier_type_id_1": 202601,
        "soldier_proportion_1": 2,
        "soldier_type_id_2": 202403,
        "soldier_proportion_2": 2,
        "soldier_type_id_3": 202302,
        "soldier_proportion_3": 1,
        "soldier_type_id_4": 202701,
        "soldier_proportion_4": 1
    },
    {
        "soldier_formation_id": 211,
        "soldier_type_id_1": 202601,
        "soldier_proportion_1": 2,
        "soldier_type_id_2": 202403,
        "soldier_proportion_2": 2,
        "soldier_type_id_3": 202303,
        "soldier_proportion_3": 1,
        "soldier_type_id_4": 202702,
        "soldier_proportion_4": 1
    },
    {
        "soldier_formation_id": 212,
        "soldier_type_id_1": 202101,
        "soldier_proportion_1": 2,
        "soldier_type_id_2": 202405,
        "soldier_proportion_2": 2,
        "soldier_type_id_3": 202301,
        "soldier_proportion_3": 1,
        "soldier_type_id_4": 202703,
        "soldier_proportion_4": 1
    },
    {
        "soldier_formation_id": 213,
        "soldier_type_id_1": 202101,
        "soldier_proportion_1": 2,
        "soldier_type_id_2": 202405,
        "soldier_proportion_2": 2,
        "soldier_type_id_3": 202302,
        "soldier_proportion_3": 1,
        "soldier_type_id_4": 202704,
        "soldier_proportion_4": 1
    },
    {
        "soldier_formation_id": 214,
        "soldier_type_id_1": 202101,
        "soldier_proportion_1": 2,
        "soldier_type_id_2": 202405,
        "soldier_proportion_2": 2,
        "soldier_type_id_3": 202303,
        "soldier_proportion_3": 1,
        "soldier_type_id_4": 202404,
        "soldier_proportion_4": 1
    },
    {
        "soldier_formation_id": 215,
        "soldier_type_id_1": 202101,
        "soldier_proportion_1": 2,
        "soldier_type_id_2": 202401,
        "soldier_proportion_2": 2,
        "soldier_type_id_3": 202301,
        "soldier_proportion_3": 1,
        "soldier_type_id_4": 202701,
        "soldier_proportion_4": 1
    },
    {
        "soldier_formation_id": 216,
        "soldier_type_id_1": 202101,
        "soldier_proportion_1": 2,
        "soldier_type_id_2": 202401,
        "soldier_proportion_2": 2,
        "soldier_type_id_3": 202302,
        "soldier_proportion_3": 1,
        "soldier_type_id_4": 202702,
        "soldier_proportion_4": 1
    },
    {
        "soldier_formation_id": 217,
        "soldier_type_id_1": 202101,
        "soldier_proportion_1": 2,
        "soldier_type_id_2": 202401,
        "soldier_proportion_2": 2,
        "soldier_type_id_3": 202303,
        "soldier_proportion_3": 1,
        "soldier_type_id_4": 202703,
        "soldier_proportion_4": 1
    },
    {
        "soldier_formation_id": 218,
        "soldier_type_id_1": 202101,
        "soldier_proportion_1": 2,
        "soldier_type_id_2": 202403,
        "soldier_proportion_2": 2,
        "soldier_type_id_3": 202301,
        "soldier_proportion_3": 1,
        "soldier_type_id_4": 202704,
        "soldier_proportion_4": 1
    },
    {
        "soldier_formation_id": 219,
        "soldier_type_id_1": 202101,
        "soldier_proportion_1": 2,
        "soldier_type_id_2": 202403,
        "soldier_proportion_2": 2,
        "soldier_type_id_3": 202302,
        "soldier_proportion_3": 1,
        "soldier_type_id_4": 202404,
        "soldier_proportion_4": 1
    },
    {
        "soldier_formation_id": 220,
        "soldier_type_id_1": 202101,
        "soldier_proportion_1": 2,
        "soldier_type_id_2": 202403,
        "soldier_proportion_2": 2,
        "soldier_type_id_3": 202303,
        "soldier_proportion_3": 1,
        "soldier_type_id_4": 202701,
        "soldier_proportion_4": 1
    },
    {
        "soldier_formation_id": 221,
        "soldier_type_id_1": 202102,
        "soldier_proportion_1": 2,
        "soldier_type_id_2": 202405,
        "soldier_proportion_2": 2,
        "soldier_type_id_3": 202301,
        "soldier_proportion_3": 1,
        "soldier_type_id_4": 202702,
        "soldier_proportion_4": 1
    },
    {
        "soldier_formation_id": 222,
        "soldier_type_id_1": 202102,
        "soldier_proportion_1": 2,
        "soldier_type_id_2": 202405,
        "soldier_proportion_2": 2,
        "soldier_type_id_3": 202302,
        "soldier_proportion_3": 1,
        "soldier_type_id_4": 202703,
        "soldier_proportion_4": 1
    },
    {
        "soldier_formation_id": 223,
        "soldier_type_id_1": 202102,
        "soldier_proportion_1": 2,
        "soldier_type_id_2": 202405,
        "soldier_proportion_2": 2,
        "soldier_type_id_3": 202303,
        "soldier_proportion_3": 1,
        "soldier_type_id_4": 202704,
        "soldier_proportion_4": 1
    },
    {
        "soldier_formation_id": 224,
        "soldier_type_id_1": 202102,
        "soldier_proportion_1": 2,
        "soldier_type_id_2": 202401,
        "soldier_proportion_2": 2,
        "soldier_type_id_3": 202301,
        "soldier_proportion_3": 1,
        "soldier_type_id_4": 202404,
        "soldier_proportion_4": 1
    },
    {
        "soldier_formation_id": 225,
        "soldier_type_id_1": 202102,
        "soldier_proportion_1": 2,
        "soldier_type_id_2": 202401,
        "soldier_proportion_2": 2,
        "soldier_type_id_3": 202302,
        "soldier_proportion_3": 1,
        "soldier_type_id_4": 202701,
        "soldier_proportion_4": 1
    },
    {
        "soldier_formation_id": 226,
        "soldier_type_id_1": 202102,
        "soldier_proportion_1": 2,
        "soldier_type_id_2": 202401,
        "soldier_proportion_2": 2,
        "soldier_type_id_3": 202303,
        "soldier_proportion_3": 1,
        "soldier_type_id_4": 202702,
        "soldier_proportion_4": 1
    },
    {
        "soldier_formation_id": 227,
        "soldier_type_id_1": 202102,
        "soldier_proportion_1": 2,
        "soldier_type_id_2": 202403,
        "soldier_proportion_2": 2,
        "soldier_type_id_3": 202301,
        "soldier_proportion_3": 1,
        "soldier_type_id_4": 202703,
        "soldier_proportion_4": 1
    },
    {
        "soldier_formation_id": 228,
        "soldier_type_id_1": 202102,
        "soldier_proportion_1": 2,
        "soldier_type_id_2": 202403,
        "soldier_proportion_2": 2,
        "soldier_type_id_3": 202302,
        "soldier_proportion_3": 1,
        "soldier_type_id_4": 202704,
        "soldier_proportion_4": 1
    },
    {
        "soldier_formation_id": 229,
        "soldier_type_id_1": 202102,
        "soldier_proportion_1": 2,
        "soldier_type_id_2": 202403,
        "soldier_proportion_2": 2,
        "soldier_type_id_3": 202303,
        "soldier_proportion_3": 1,
        "soldier_type_id_4": 202404,
        "soldier_proportion_4": 1
    },
    {
        "soldier_formation_id": 230,
        "soldier_type_id_1": 202502,
        "soldier_proportion_1": 2,
        "soldier_type_id_2": 202405,
        "soldier_proportion_2": 2,
        "soldier_type_id_3": 202701,
        "soldier_proportion_3": 1,
        "soldier_type_id_4": "",
        "soldier_proportion_4": ""
    },
    {
        "soldier_formation_id": 231,
        "soldier_type_id_1": 202502,
        "soldier_proportion_1": 2,
        "soldier_type_id_2": 202405,
        "soldier_proportion_2": 2,
        "soldier_type_id_3": 202702,
        "soldier_proportion_3": 1,
        "soldier_type_id_4": "",
        "soldier_proportion_4": ""
    },
    {
        "soldier_formation_id": 232,
        "soldier_type_id_1": 202502,
        "soldier_proportion_1": 2,
        "soldier_type_id_2": 202405,
        "soldier_proportion_2": 2,
        "soldier_type_id_3": 202703,
        "soldier_proportion_3": 1,
        "soldier_type_id_4": "",
        "soldier_proportion_4": ""
    },
    {
        "soldier_formation_id": 233,
        "soldier_type_id_1": 202502,
        "soldier_proportion_1": 2,
        "soldier_type_id_2": 202401,
        "soldier_proportion_2": 2,
        "soldier_type_id_3": 202704,
        "soldier_proportion_3": 1,
        "soldier_type_id_4": "",
        "soldier_proportion_4": ""
    },
    {
        "soldier_formation_id": 234,
        "soldier_type_id_1": 202502,
        "soldier_proportion_1": 2,
        "soldier_type_id_2": 202401,
        "soldier_proportion_2": 2,
        "soldier_type_id_3": 202404,
        "soldier_proportion_3": 1,
        "soldier_type_id_4": "",
        "soldier_proportion_4": ""
    },
    {
        "soldier_formation_id": 235,
        "soldier_type_id_1": 202502,
        "soldier_proportion_1": 2,
        "soldier_type_id_2": 202401,
        "soldier_proportion_2": 2,
        "soldier_type_id_3": 202701,
        "soldier_proportion_3": 1,
        "soldier_type_id_4": "",
        "soldier_proportion_4": ""
    },
    {
        "soldier_formation_id": 236,
        "soldier_type_id_1": 202502,
        "soldier_proportion_1": 2,
        "soldier_type_id_2": 202403,
        "soldier_proportion_2": 2,
        "soldier_type_id_3": 202702,
        "soldier_proportion_3": 1,
        "soldier_type_id_4": "",
        "soldier_proportion_4": ""
    },
    {
        "soldier_formation_id": 237,
        "soldier_type_id_1": 202502,
        "soldier_proportion_1": 2,
        "soldier_type_id_2": 202403,
        "soldier_proportion_2": 2,
        "soldier_type_id_3": 202703,
        "soldier_proportion_3": 1,
        "soldier_type_id_4": "",
        "soldier_proportion_4": ""
    },
    {
        "soldier_formation_id": 238,
        "soldier_type_id_1": 202502,
        "soldier_proportion_1": 2,
        "soldier_type_id_2": 202403,
        "soldier_proportion_2": 2,
        "soldier_type_id_3": 202704,
        "soldier_proportion_3": 1,
        "soldier_type_id_4": "",
        "soldier_proportion_4": ""
    },
    {
        "soldier_formation_id": 239,
        "soldier_type_id_1": 202501,
        "soldier_proportion_1": 2,
        "soldier_type_id_2": 202405,
        "soldier_proportion_2": 2,
        "soldier_type_id_3": 202404,
        "soldier_proportion_3": 1,
        "soldier_type_id_4": "",
        "soldier_proportion_4": ""
    },
    {
        "soldier_formation_id": 240,
        "soldier_type_id_1": 202501,
        "soldier_proportion_1": 2,
        "soldier_type_id_2": 202405,
        "soldier_proportion_2": 2,
        "soldier_type_id_3": 202701,
        "soldier_proportion_3": 1,
        "soldier_type_id_4": "",
        "soldier_proportion_4": ""
    },
    {
        "soldier_formation_id": 241,
        "soldier_type_id_1": 202501,
        "soldier_proportion_1": 2,
        "soldier_type_id_2": 202405,
        "soldier_proportion_2": 2,
        "soldier_type_id_3": 202702,
        "soldier_proportion_3": 1,
        "soldier_type_id_4": "",
        "soldier_proportion_4": ""
    },
    {
        "soldier_formation_id": 242,
        "soldier_type_id_1": 202501,
        "soldier_proportion_1": 2,
        "soldier_type_id_2": 202401,
        "soldier_proportion_2": 2,
        "soldier_type_id_3": 202703,
        "soldier_proportion_3": 1,
        "soldier_type_id_4": "",
        "soldier_proportion_4": ""
    },
    {
        "soldier_formation_id": 243,
        "soldier_type_id_1": 202501,
        "soldier_proportion_1": 2,
        "soldier_type_id_2": 202401,
        "soldier_proportion_2": 2,
        "soldier_type_id_3": 202704,
        "soldier_proportion_3": 1,
        "soldier_type_id_4": "",
        "soldier_proportion_4": ""
    },
    {
        "soldier_formation_id": 244,
        "soldier_type_id_1": 202501,
        "soldier_proportion_1": 2,
        "soldier_type_id_2": 202401,
        "soldier_proportion_2": 2,
        "soldier_type_id_3": 202404,
        "soldier_proportion_3": 1,
        "soldier_type_id_4": "",
        "soldier_proportion_4": ""
    },
    {
        "soldier_formation_id": 245,
        "soldier_type_id_1": 202501,
        "soldier_proportion_1": 2,
        "soldier_type_id_2": 202403,
        "soldier_proportion_2": 2,
        "soldier_type_id_3": 202701,
        "soldier_proportion_3": 1,
        "soldier_type_id_4": "",
        "soldier_proportion_4": ""
    },
    {
        "soldier_formation_id": 246,
        "soldier_type_id_1": 202501,
        "soldier_proportion_1": 2,
        "soldier_type_id_2": 202403,
        "soldier_proportion_2": 2,
        "soldier_type_id_3": 202702,
        "soldier_proportion_3": 1,
        "soldier_type_id_4": "",
        "soldier_proportion_4": ""
    },
    {
        "soldier_formation_id": 247,
        "soldier_type_id_1": 202501,
        "soldier_proportion_1": 2,
        "soldier_type_id_2": 202403,
        "soldier_proportion_2": 2,
        "soldier_type_id_3": 202703,
        "soldier_proportion_3": 1,
        "soldier_type_id_4": "",
        "soldier_proportion_4": ""
    },
    {
        "soldier_formation_id": 248,
        "soldier_type_id_1": 202601,
        "soldier_proportion_1": 2,
        "soldier_type_id_2": 202405,
        "soldier_proportion_2": 2,
        "soldier_type_id_3": 202704,
        "soldier_proportion_3": 1,
        "soldier_type_id_4": "",
        "soldier_proportion_4": ""
    },
    {
        "soldier_formation_id": 249,
        "soldier_type_id_1": 202601,
        "soldier_proportion_1": 2,
        "soldier_type_id_2": 202405,
        "soldier_proportion_2": 2,
        "soldier_type_id_3": 202404,
        "soldier_proportion_3": 1,
        "soldier_type_id_4": "",
        "soldier_proportion_4": ""
    },
    {
        "soldier_formation_id": 250,
        "soldier_type_id_1": 202601,
        "soldier_proportion_1": 2,
        "soldier_type_id_2": 202405,
        "soldier_proportion_2": 2,
        "soldier_type_id_3": 202701,
        "soldier_proportion_3": 1,
        "soldier_type_id_4": "",
        "soldier_proportion_4": ""
    },
    {
        "soldier_formation_id": 251,
        "soldier_type_id_1": 202601,
        "soldier_proportion_1": 2,
        "soldier_type_id_2": 202401,
        "soldier_proportion_2": 2,
        "soldier_type_id_3": 202702,
        "soldier_proportion_3": 1,
        "soldier_type_id_4": "",
        "soldier_proportion_4": ""
    },
    {
        "soldier_formation_id": 252,
        "soldier_type_id_1": 202601,
        "soldier_proportion_1": 2,
        "soldier_type_id_2": 202401,
        "soldier_proportion_2": 2,
        "soldier_type_id_3": 202703,
        "soldier_proportion_3": 1,
        "soldier_type_id_4": "",
        "soldier_proportion_4": ""
    },
    {
        "soldier_formation_id": 253,
        "soldier_type_id_1": 202601,
        "soldier_proportion_1": 2,
        "soldier_type_id_2": 202401,
        "soldier_proportion_2": 2,
        "soldier_type_id_3": 202704,
        "soldier_proportion_3": 1,
        "soldier_type_id_4": "",
        "soldier_proportion_4": ""
    },
    {
        "soldier_formation_id": 254,
        "soldier_type_id_1": 202601,
        "soldier_proportion_1": 2,
        "soldier_type_id_2": 202403,
        "soldier_proportion_2": 2,
        "soldier_type_id_3": 202404,
        "soldier_proportion_3": 1,
        "soldier_type_id_4": "",
        "soldier_proportion_4": ""
    },
    {
        "soldier_formation_id": 255,
        "soldier_type_id_1": 202601,
        "soldier_proportion_1": 2,
        "soldier_type_id_2": 202403,
        "soldier_proportion_2": 2,
        "soldier_type_id_3": 202701,
        "soldier_proportion_3": 1,
        "soldier_type_id_4": "",
        "soldier_proportion_4": ""
    },
    {
        "soldier_formation_id": 256,
        "soldier_type_id_1": 202601,
        "soldier_proportion_1": 2,
        "soldier_type_id_2": 202403,
        "soldier_proportion_2": 2,
        "soldier_type_id_3": 202702,
        "soldier_proportion_3": 1,
        "soldier_type_id_4": "",
        "soldier_proportion_4": ""
    },
    {
        "soldier_formation_id": 257,
        "soldier_type_id_1": 202101,
        "soldier_proportion_1": 2,
        "soldier_type_id_2": 202405,
        "soldier_proportion_2": 2,
        "soldier_type_id_3": 202703,
        "soldier_proportion_3": 1,
        "soldier_type_id_4": "",
        "soldier_proportion_4": ""
    },
    {
        "soldier_formation_id": 258,
        "soldier_type_id_1": 202101,
        "soldier_proportion_1": 2,
        "soldier_type_id_2": 202405,
        "soldier_proportion_2": 2,
        "soldier_type_id_3": 202704,
        "soldier_proportion_3": 1,
        "soldier_type_id_4": "",
        "soldier_proportion_4": ""
    },
    {
        "soldier_formation_id": 259,
        "soldier_type_id_1": 202101,
        "soldier_proportion_1": 2,
        "soldier_type_id_2": 202405,
        "soldier_proportion_2": 2,
        "soldier_type_id_3": 202404,
        "soldier_proportion_3": 1,
        "soldier_type_id_4": "",
        "soldier_proportion_4": ""
    },
    {
        "soldier_formation_id": 260,
        "soldier_type_id_1": 202101,
        "soldier_proportion_1": 2,
        "soldier_type_id_2": 202401,
        "soldier_proportion_2": 2,
        "soldier_type_id_3": 202701,
        "soldier_proportion_3": 1,
        "soldier_type_id_4": "",
        "soldier_proportion_4": ""
    },
    {
        "soldier_formation_id": 261,
        "soldier_type_id_1": 202101,
        "soldier_proportion_1": 2,
        "soldier_type_id_2": 202401,
        "soldier_proportion_2": 2,
        "soldier_type_id_3": 202702,
        "soldier_proportion_3": 1,
        "soldier_type_id_4": "",
        "soldier_proportion_4": ""
    },
    {
        "soldier_formation_id": 262,
        "soldier_type_id_1": 202101,
        "soldier_proportion_1": 2,
        "soldier_type_id_2": 202401,
        "soldier_proportion_2": 2,
        "soldier_type_id_3": 202703,
        "soldier_proportion_3": 1,
        "soldier_type_id_4": "",
        "soldier_proportion_4": ""
    },
    {
        "soldier_formation_id": 263,
        "soldier_type_id_1": 202101,
        "soldier_proportion_1": 2,
        "soldier_type_id_2": 202403,
        "soldier_proportion_2": 2,
        "soldier_type_id_3": 202704,
        "soldier_proportion_3": 1,
        "soldier_type_id_4": "",
        "soldier_proportion_4": ""
    },
    {
        "soldier_formation_id": 264,
        "soldier_type_id_1": 202101,
        "soldier_proportion_1": 2,
        "soldier_type_id_2": 202403,
        "soldier_proportion_2": 2,
        "soldier_type_id_3": 202404,
        "soldier_proportion_3": 1,
        "soldier_type_id_4": "",
        "soldier_proportion_4": ""
    },
    {
        "soldier_formation_id": 265,
        "soldier_type_id_1": 202101,
        "soldier_proportion_1": 2,
        "soldier_type_id_2": 202403,
        "soldier_proportion_2": 2,
        "soldier_type_id_3": 202701,
        "soldier_proportion_3": 1,
        "soldier_type_id_4": "",
        "soldier_proportion_4": ""
    },
    {
        "soldier_formation_id": 266,
        "soldier_type_id_1": 202102,
        "soldier_proportion_1": 2,
        "soldier_type_id_2": 202405,
        "soldier_proportion_2": 2,
        "soldier_type_id_3": 202702,
        "soldier_proportion_3": 1,
        "soldier_type_id_4": "",
        "soldier_proportion_4": ""
    },
    {
        "soldier_formation_id": 267,
        "soldier_type_id_1": 202102,
        "soldier_proportion_1": 2,
        "soldier_type_id_2": 202405,
        "soldier_proportion_2": 2,
        "soldier_type_id_3": 202703,
        "soldier_proportion_3": 1,
        "soldier_type_id_4": "",
        "soldier_proportion_4": ""
    },
    {
        "soldier_formation_id": 268,
        "soldier_type_id_1": 202102,
        "soldier_proportion_1": 2,
        "soldier_type_id_2": 202405,
        "soldier_proportion_2": 2,
        "soldier_type_id_3": 202704,
        "soldier_proportion_3": 1,
        "soldier_type_id_4": "",
        "soldier_proportion_4": ""
    },
    {
        "soldier_formation_id": 269,
        "soldier_type_id_1": 202102,
        "soldier_proportion_1": 2,
        "soldier_type_id_2": 202401,
        "soldier_proportion_2": 2,
        "soldier_type_id_3": 202404,
        "soldier_proportion_3": 1,
        "soldier_type_id_4": "",
        "soldier_proportion_4": ""
    },
    {
        "soldier_formation_id": 270,
        "soldier_type_id_1": 202102,
        "soldier_proportion_1": 2,
        "soldier_type_id_2": 202401,
        "soldier_proportion_2": 2,
        "soldier_type_id_3": 202701,
        "soldier_proportion_3": 1,
        "soldier_type_id_4": "",
        "soldier_proportion_4": ""
    },
    {
        "soldier_formation_id": 271,
        "soldier_type_id_1": 202102,
        "soldier_proportion_1": 2,
        "soldier_type_id_2": 202401,
        "soldier_proportion_2": 2,
        "soldier_type_id_3": 202702,
        "soldier_proportion_3": 1,
        "soldier_type_id_4": "",
        "soldier_proportion_4": ""
    },
    {
        "soldier_formation_id": 272,
        "soldier_type_id_1": 202102,
        "soldier_proportion_1": 2,
        "soldier_type_id_2": 202403,
        "soldier_proportion_2": 2,
        "soldier_type_id_3": 202703,
        "soldier_proportion_3": 1,
        "soldier_type_id_4": "",
        "soldier_proportion_4": ""
    },
    {
        "soldier_formation_id": 273,
        "soldier_type_id_1": 202102,
        "soldier_proportion_1": 2,
        "soldier_type_id_2": 202403,
        "soldier_proportion_2": 2,
        "soldier_type_id_3": 202704,
        "soldier_proportion_3": 1,
        "soldier_type_id_4": "",
        "soldier_proportion_4": ""
    },
    {
        "soldier_formation_id": 274,
        "soldier_type_id_1": 202102,
        "soldier_proportion_1": 2,
        "soldier_type_id_2": 202403,
        "soldier_proportion_2": 2,
        "soldier_type_id_3": 202404,
        "soldier_proportion_3": 1,
        "soldier_type_id_4": "",
        "soldier_proportion_4": ""
    },
    {
        "soldier_formation_id": 275,
        "soldier_type_id_1": 202304,
        "soldier_proportion_1": 1,
        "soldier_type_id_2": "",
        "soldier_proportion_2": "",
        "soldier_type_id_3": "",
        "soldier_proportion_3": "",
        "soldier_type_id_4": "",
        "soldier_proportion_4": ""
    },
    {
        "soldier_formation_id": 276,
        "soldier_type_id_1": 202502,
        "soldier_proportion_1": 2,
        "soldier_type_id_2": 202405,
        "soldier_proportion_2": 2,
        "soldier_type_id_3": 202304,
        "soldier_proportion_3": 1,
        "soldier_type_id_4": 202701,
        "soldier_proportion_4": 1
    },
    {
        "soldier_formation_id": 277,
        "soldier_type_id_1": 202502,
        "soldier_proportion_1": 2,
        "soldier_type_id_2": 202405,
        "soldier_proportion_2": 2,
        "soldier_type_id_3": 202304,
        "soldier_proportion_3": 1,
        "soldier_type_id_4": 202702,
        "soldier_proportion_4": 1
    },
    {
        "soldier_formation_id": 278,
        "soldier_type_id_1": 202502,
        "soldier_proportion_1": 2,
        "soldier_type_id_2": 202405,
        "soldier_proportion_2": 2,
        "soldier_type_id_3": 202304,
        "soldier_proportion_3": 1,
        "soldier_type_id_4": 202703,
        "soldier_proportion_4": 1
    },
    {
        "soldier_formation_id": 279,
        "soldier_type_id_1": 202502,
        "soldier_proportion_1": 2,
        "soldier_type_id_2": 202401,
        "soldier_proportion_2": 2,
        "soldier_type_id_3": 202304,
        "soldier_proportion_3": 1,
        "soldier_type_id_4": 202704,
        "soldier_proportion_4": 1
    },
    {
        "soldier_formation_id": 280,
        "soldier_type_id_1": 202502,
        "soldier_proportion_1": 2,
        "soldier_type_id_2": 202401,
        "soldier_proportion_2": 2,
        "soldier_type_id_3": 202304,
        "soldier_proportion_3": 1,
        "soldier_type_id_4": 202404,
        "soldier_proportion_4": 1
    },
    {
        "soldier_formation_id": 281,
        "soldier_type_id_1": 202502,
        "soldier_proportion_1": 2,
        "soldier_type_id_2": 202401,
        "soldier_proportion_2": 2,
        "soldier_type_id_3": 202304,
        "soldier_proportion_3": 1,
        "soldier_type_id_4": 202701,
        "soldier_proportion_4": 1
    },
    {
        "soldier_formation_id": 282,
        "soldier_type_id_1": 202502,
        "soldier_proportion_1": 2,
        "soldier_type_id_2": 202403,
        "soldier_proportion_2": 2,
        "soldier_type_id_3": 202304,
        "soldier_proportion_3": 1,
        "soldier_type_id_4": 202702,
        "soldier_proportion_4": 1
    },
    {
        "soldier_formation_id": 283,
        "soldier_type_id_1": 202502,
        "soldier_proportion_1": 2,
        "soldier_type_id_2": 202403,
        "soldier_proportion_2": 2,
        "soldier_type_id_3": 202304,
        "soldier_proportion_3": 1,
        "soldier_type_id_4": 202703,
        "soldier_proportion_4": 1
    },
    {
        "soldier_formation_id": 284,
        "soldier_type_id_1": 202502,
        "soldier_proportion_1": 2,
        "soldier_type_id_2": 202403,
        "soldier_proportion_2": 2,
        "soldier_type_id_3": 202304,
        "soldier_proportion_3": 1,
        "soldier_type_id_4": 202704,
        "soldier_proportion_4": 1
    },
    {
        "soldier_formation_id": 285,
        "soldier_type_id_1": 202501,
        "soldier_proportion_1": 2,
        "soldier_type_id_2": 202405,
        "soldier_proportion_2": 2,
        "soldier_type_id_3": 202304,
        "soldier_proportion_3": 1,
        "soldier_type_id_4": 202404,
        "soldier_proportion_4": 1
    },
    {
        "soldier_formation_id": 286,
        "soldier_type_id_1": 202501,
        "soldier_proportion_1": 2,
        "soldier_type_id_2": 202405,
        "soldier_proportion_2": 2,
        "soldier_type_id_3": 202304,
        "soldier_proportion_3": 1,
        "soldier_type_id_4": 202701,
        "soldier_proportion_4": 1
    },
    {
        "soldier_formation_id": 287,
        "soldier_type_id_1": 202501,
        "soldier_proportion_1": 2,
        "soldier_type_id_2": 202405,
        "soldier_proportion_2": 2,
        "soldier_type_id_3": 202304,
        "soldier_proportion_3": 1,
        "soldier_type_id_4": 202702,
        "soldier_proportion_4": 1
    },
    {
        "soldier_formation_id": 288,
        "soldier_type_id_1": 202501,
        "soldier_proportion_1": 2,
        "soldier_type_id_2": 202401,
        "soldier_proportion_2": 2,
        "soldier_type_id_3": 202304,
        "soldier_proportion_3": 1,
        "soldier_type_id_4": 202703,
        "soldier_proportion_4": 1
    },
    {
        "soldier_formation_id": 289,
        "soldier_type_id_1": 202501,
        "soldier_proportion_1": 2,
        "soldier_type_id_2": 202401,
        "soldier_proportion_2": 2,
        "soldier_type_id_3": 202304,
        "soldier_proportion_3": 1,
        "soldier_type_id_4": 202704,
        "soldier_proportion_4": 1
    },
    {
        "soldier_formation_id": 290,
        "soldier_type_id_1": 202501,
        "soldier_proportion_1": 2,
        "soldier_type_id_2": 202401,
        "soldier_proportion_2": 2,
        "soldier_type_id_3": 202304,
        "soldier_proportion_3": 1,
        "soldier_type_id_4": 202404,
        "soldier_proportion_4": 1
    },
    {
        "soldier_formation_id": 291,
        "soldier_type_id_1": 202501,
        "soldier_proportion_1": 2,
        "soldier_type_id_2": 202403,
        "soldier_proportion_2": 2,
        "soldier_type_id_3": 202304,
        "soldier_proportion_3": 1,
        "soldier_type_id_4": 202701,
        "soldier_proportion_4": 1
    },
    {
        "soldier_formation_id": 292,
        "soldier_type_id_1": 202501,
        "soldier_proportion_1": 2,
        "soldier_type_id_2": 202403,
        "soldier_proportion_2": 2,
        "soldier_type_id_3": 202304,
        "soldier_proportion_3": 1,
        "soldier_type_id_4": 202702,
        "soldier_proportion_4": 1
    },
    {
        "soldier_formation_id": 293,
        "soldier_type_id_1": 202501,
        "soldier_proportion_1": 2,
        "soldier_type_id_2": 202403,
        "soldier_proportion_2": 2,
        "soldier_type_id_3": 202304,
        "soldier_proportion_3": 1,
        "soldier_type_id_4": 202703,
        "soldier_proportion_4": 1
    },
    {
        "soldier_formation_id": 294,
        "soldier_type_id_1": 202601,
        "soldier_proportion_1": 2,
        "soldier_type_id_2": 202405,
        "soldier_proportion_2": 2,
        "soldier_type_id_3": 202304,
        "soldier_proportion_3": 1,
        "soldier_type_id_4": 202704,
        "soldier_proportion_4": 1
    },
    {
        "soldier_formation_id": 295,
        "soldier_type_id_1": 202601,
        "soldier_proportion_1": 2,
        "soldier_type_id_2": 202405,
        "soldier_proportion_2": 2,
        "soldier_type_id_3": 202304,
        "soldier_proportion_3": 1,
        "soldier_type_id_4": 202404,
        "soldier_proportion_4": 1
    },
    {
        "soldier_formation_id": 296,
        "soldier_type_id_1": 202601,
        "soldier_proportion_1": 2,
        "soldier_type_id_2": 202405,
        "soldier_proportion_2": 2,
        "soldier_type_id_3": 202304,
        "soldier_proportion_3": 1,
        "soldier_type_id_4": 202701,
        "soldier_proportion_4": 1
    },
    {
        "soldier_formation_id": 297,
        "soldier_type_id_1": 202601,
        "soldier_proportion_1": 2,
        "soldier_type_id_2": 202401,
        "soldier_proportion_2": 2,
        "soldier_type_id_3": 202304,
        "soldier_proportion_3": 1,
        "soldier_type_id_4": 202702,
        "soldier_proportion_4": 1
    },
    {
        "soldier_formation_id": 298,
        "soldier_type_id_1": 202601,
        "soldier_proportion_1": 2,
        "soldier_type_id_2": 202401,
        "soldier_proportion_2": 2,
        "soldier_type_id_3": 202304,
        "soldier_proportion_3": 1,
        "soldier_type_id_4": 202703,
        "soldier_proportion_4": 1
    },
    {
        "soldier_formation_id": 299,
        "soldier_type_id_1": 202601,
        "soldier_proportion_1": 2,
        "soldier_type_id_2": 202401,
        "soldier_proportion_2": 2,
        "soldier_type_id_3": 202304,
        "soldier_proportion_3": 1,
        "soldier_type_id_4": 202704,
        "soldier_proportion_4": 1
    },
    {
        "soldier_formation_id": 300,
        "soldier_type_id_1": 202601,
        "soldier_proportion_1": 2,
        "soldier_type_id_2": 202403,
        "soldier_proportion_2": 2,
        "soldier_type_id_3": 202304,
        "soldier_proportion_3": 1,
        "soldier_type_id_4": 202404,
        "soldier_proportion_4": 1
    },
    {
        "soldier_formation_id": 301,
        "soldier_type_id_1": 202601,
        "soldier_proportion_1": 2,
        "soldier_type_id_2": 202403,
        "soldier_proportion_2": 2,
        "soldier_type_id_3": 202304,
        "soldier_proportion_3": 1,
        "soldier_type_id_4": 202701,
        "soldier_proportion_4": 1
    },
    {
        "soldier_formation_id": 302,
        "soldier_type_id_1": 202601,
        "soldier_proportion_1": 2,
        "soldier_type_id_2": 202403,
        "soldier_proportion_2": 2,
        "soldier_type_id_3": 202304,
        "soldier_proportion_3": 1,
        "soldier_type_id_4": 202702,
        "soldier_proportion_4": 1
    },
    {
        "soldier_formation_id": 303,
        "soldier_type_id_1": 202101,
        "soldier_proportion_1": 2,
        "soldier_type_id_2": 202405,
        "soldier_proportion_2": 2,
        "soldier_type_id_3": 202304,
        "soldier_proportion_3": 1,
        "soldier_type_id_4": 202703,
        "soldier_proportion_4": 1
    },
    {
        "soldier_formation_id": 304,
        "soldier_type_id_1": 202101,
        "soldier_proportion_1": 2,
        "soldier_type_id_2": 202405,
        "soldier_proportion_2": 2,
        "soldier_type_id_3": 202304,
        "soldier_proportion_3": 1,
        "soldier_type_id_4": 202704,
        "soldier_proportion_4": 1
    },
    {
        "soldier_formation_id": 305,
        "soldier_type_id_1": 202101,
        "soldier_proportion_1": 2,
        "soldier_type_id_2": 202405,
        "soldier_proportion_2": 2,
        "soldier_type_id_3": 202304,
        "soldier_proportion_3": 1,
        "soldier_type_id_4": 202404,
        "soldier_proportion_4": 1
    },
    {
        "soldier_formation_id": 306,
        "soldier_type_id_1": 202101,
        "soldier_proportion_1": 2,
        "soldier_type_id_2": 202401,
        "soldier_proportion_2": 2,
        "soldier_type_id_3": 202304,
        "soldier_proportion_3": 1,
        "soldier_type_id_4": 202701,
        "soldier_proportion_4": 1
    },
    {
        "soldier_formation_id": 307,
        "soldier_type_id_1": 202101,
        "soldier_proportion_1": 2,
        "soldier_type_id_2": 202401,
        "soldier_proportion_2": 2,
        "soldier_type_id_3": 202304,
        "soldier_proportion_3": 1,
        "soldier_type_id_4": 202702,
        "soldier_proportion_4": 1
    },
    {
        "soldier_formation_id": 308,
        "soldier_type_id_1": 202101,
        "soldier_proportion_1": 2,
        "soldier_type_id_2": 202401,
        "soldier_proportion_2": 2,
        "soldier_type_id_3": 202304,
        "soldier_proportion_3": 1,
        "soldier_type_id_4": 202703,
        "soldier_proportion_4": 1
    },
    {
        "soldier_formation_id": 309,
        "soldier_type_id_1": 202101,
        "soldier_proportion_1": 2,
        "soldier_type_id_2": 202403,
        "soldier_proportion_2": 2,
        "soldier_type_id_3": 202304,
        "soldier_proportion_3": 1,
        "soldier_type_id_4": 202704,
        "soldier_proportion_4": 1
    },
    {
        "soldier_formation_id": 310,
        "soldier_type_id_1": 202101,
        "soldier_proportion_1": 2,
        "soldier_type_id_2": 202403,
        "soldier_proportion_2": 2,
        "soldier_type_id_3": 202304,
        "soldier_proportion_3": 1,
        "soldier_type_id_4": 202404,
        "soldier_proportion_4": 1
    },
    {
        "soldier_formation_id": 311,
        "soldier_type_id_1": 202101,
        "soldier_proportion_1": 2,
        "soldier_type_id_2": 202403,
        "soldier_proportion_2": 2,
        "soldier_type_id_3": 202304,
        "soldier_proportion_3": 1,
        "soldier_type_id_4": 202701,
        "soldier_proportion_4": 1
    },
    {
        "soldier_formation_id": 312,
        "soldier_type_id_1": 202102,
        "soldier_proportion_1": 2,
        "soldier_type_id_2": 202405,
        "soldier_proportion_2": 2,
        "soldier_type_id_3": 202304,
        "soldier_proportion_3": 1,
        "soldier_type_id_4": 202702,
        "soldier_proportion_4": 1
    },
    {
        "soldier_formation_id": 313,
        "soldier_type_id_1": 202102,
        "soldier_proportion_1": 2,
        "soldier_type_id_2": 202405,
        "soldier_proportion_2": 2,
        "soldier_type_id_3": 202304,
        "soldier_proportion_3": 1,
        "soldier_type_id_4": 202703,
        "soldier_proportion_4": 1
    },
    {
        "soldier_formation_id": 314,
        "soldier_type_id_1": 202102,
        "soldier_proportion_1": 2,
        "soldier_type_id_2": 202405,
        "soldier_proportion_2": 2,
        "soldier_type_id_3": 202304,
        "soldier_proportion_3": 1,
        "soldier_type_id_4": 202704,
        "soldier_proportion_4": 1
    },
    {
        "soldier_formation_id": 315,
        "soldier_type_id_1": 202102,
        "soldier_proportion_1": 2,
        "soldier_type_id_2": 202401,
        "soldier_proportion_2": 2,
        "soldier_type_id_3": 202304,
        "soldier_proportion_3": 1,
        "soldier_type_id_4": 202404,
        "soldier_proportion_4": 1
    },
    {
        "soldier_formation_id": 316,
        "soldier_type_id_1": 202102,
        "soldier_proportion_1": 2,
        "soldier_type_id_2": 202401,
        "soldier_proportion_2": 2,
        "soldier_type_id_3": 202304,
        "soldier_proportion_3": 1,
        "soldier_type_id_4": 202701,
        "soldier_proportion_4": 1
    },
    {
        "soldier_formation_id": 317,
        "soldier_type_id_1": 202102,
        "soldier_proportion_1": 2,
        "soldier_type_id_2": 202401,
        "soldier_proportion_2": 2,
        "soldier_type_id_3": 202304,
        "soldier_proportion_3": 1,
        "soldier_type_id_4": 202702,
        "soldier_proportion_4": 1
    },
    {
        "soldier_formation_id": 318,
        "soldier_type_id_1": 202102,
        "soldier_proportion_1": 2,
        "soldier_type_id_2": 202403,
        "soldier_proportion_2": 2,
        "soldier_type_id_3": 202304,
        "soldier_proportion_3": 1,
        "soldier_type_id_4": 202703,
        "soldier_proportion_4": 1
    },
    {
        "soldier_formation_id": 319,
        "soldier_type_id_1": 202102,
        "soldier_proportion_1": 2,
        "soldier_type_id_2": 202403,
        "soldier_proportion_2": 2,
        "soldier_type_id_3": 202304,
        "soldier_proportion_3": 1,
        "soldier_type_id_4": 202704,
        "soldier_proportion_4": 1
    },
    {
        "soldier_formation_id": 320,
        "soldier_type_id_1": 202102,
        "soldier_proportion_1": 2,
        "soldier_type_id_2": 202403,
        "soldier_proportion_2": 2,
        "soldier_type_id_3": 202304,
        "soldier_proportion_3": 1,
        "soldier_type_id_4": 202404,
        "soldier_proportion_4": 1
    },
    {
        "soldier_formation_id": 321,
        "soldier_type_id_1": 202502,
        "soldier_proportion_1": 2,
        "soldier_type_id_2": 202405,
        "soldier_proportion_2": 2,
        "soldier_type_id_3": 202304,
        "soldier_proportion_3": 1,
        "soldier_type_id_4": "",
        "soldier_proportion_4": ""
    },
    {
        "soldier_formation_id": 322,
        "soldier_type_id_1": 202502,
        "soldier_proportion_1": 2,
        "soldier_type_id_2": 202401,
        "soldier_proportion_2": 2,
        "soldier_type_id_3": 202304,
        "soldier_proportion_3": 1,
        "soldier_type_id_4": "",
        "soldier_proportion_4": ""
    },
    {
        "soldier_formation_id": 323,
        "soldier_type_id_1": 202502,
        "soldier_proportion_1": 2,
        "soldier_type_id_2": 202403,
        "soldier_proportion_2": 2,
        "soldier_type_id_3": 202304,
        "soldier_proportion_3": 1,
        "soldier_type_id_4": "",
        "soldier_proportion_4": ""
    },
    {
        "soldier_formation_id": 324,
        "soldier_type_id_1": 202501,
        "soldier_proportion_1": 2,
        "soldier_type_id_2": 202405,
        "soldier_proportion_2": 2,
        "soldier_type_id_3": 202304,
        "soldier_proportion_3": 1,
        "soldier_type_id_4": "",
        "soldier_proportion_4": ""
    },
    {
        "soldier_formation_id": 325,
        "soldier_type_id_1": 202501,
        "soldier_proportion_1": 2,
        "soldier_type_id_2": 202401,
        "soldier_proportion_2": 2,
        "soldier_type_id_3": 202304,
        "soldier_proportion_3": 1,
        "soldier_type_id_4": "",
        "soldier_proportion_4": ""
    },
    {
        "soldier_formation_id": 326,
        "soldier_type_id_1": 202501,
        "soldier_proportion_1": 2,
        "soldier_type_id_2": 202403,
        "soldier_proportion_2": 2,
        "soldier_type_id_3": 202304,
        "soldier_proportion_3": 1,
        "soldier_type_id_4": "",
        "soldier_proportion_4": ""
    },
    {
        "soldier_formation_id": 327,
        "soldier_type_id_1": 202601,
        "soldier_proportion_1": 2,
        "soldier_type_id_2": 202405,
        "soldier_proportion_2": 2,
        "soldier_type_id_3": 202304,
        "soldier_proportion_3": 1,
        "soldier_type_id_4": "",
        "soldier_proportion_4": ""
    },
    {
        "soldier_formation_id": 328,
        "soldier_type_id_1": 202601,
        "soldier_proportion_1": 2,
        "soldier_type_id_2": 202401,
        "soldier_proportion_2": 2,
        "soldier_type_id_3": 202304,
        "soldier_proportion_3": 1,
        "soldier_type_id_4": "",
        "soldier_proportion_4": ""
    },
    {
        "soldier_formation_id": 329,
        "soldier_type_id_1": 202601,
        "soldier_proportion_1": 2,
        "soldier_type_id_2": 202403,
        "soldier_proportion_2": 2,
        "soldier_type_id_3": 202304,
        "soldier_proportion_3": 1,
        "soldier_type_id_4": "",
        "soldier_proportion_4": ""
    },
    {
        "soldier_formation_id": 330,
        "soldier_type_id_1": 202101,
        "soldier_proportion_1": 2,
        "soldier_type_id_2": 202405,
        "soldier_proportion_2": 2,
        "soldier_type_id_3": 202304,
        "soldier_proportion_3": 1,
        "soldier_type_id_4": "",
        "soldier_proportion_4": ""
    },
    {
        "soldier_formation_id": 331,
        "soldier_type_id_1": 202101,
        "soldier_proportion_1": 2,
        "soldier_type_id_2": 202401,
        "soldier_proportion_2": 2,
        "soldier_type_id_3": 202304,
        "soldier_proportion_3": 1,
        "soldier_type_id_4": "",
        "soldier_proportion_4": ""
    },
    {
        "soldier_formation_id": 332,
        "soldier_type_id_1": 202101,
        "soldier_proportion_1": 2,
        "soldier_type_id_2": 202403,
        "soldier_proportion_2": 2,
        "soldier_type_id_3": 202304,
        "soldier_proportion_3": 1,
        "soldier_type_id_4": "",
        "soldier_proportion_4": ""
    },
    {
        "soldier_formation_id": 333,
        "soldier_type_id_1": 202102,
        "soldier_proportion_1": 2,
        "soldier_type_id_2": 202405,
        "soldier_proportion_2": 2,
        "soldier_type_id_3": 202304,
        "soldier_proportion_3": 1,
        "soldier_type_id_4": "",
        "soldier_proportion_4": ""
    },
    {
        "soldier_formation_id": 334,
        "soldier_type_id_1": 202102,
        "soldier_proportion_1": 2,
        "soldier_type_id_2": 202401,
        "soldier_proportion_2": 2,
        "soldier_type_id_3": 202304,
        "soldier_proportion_3": 1,
        "soldier_type_id_4": "",
        "soldier_proportion_4": ""
    },
    {
        "soldier_formation_id": 335,
        "soldier_type_id_1": 202102,
        "soldier_proportion_1": 2,
        "soldier_type_id_2": 202403,
        "soldier_proportion_2": 2,
        "soldier_type_id_3": 202304,
        "soldier_proportion_3": 1,
        "soldier_type_id_4": "",
        "soldier_proportion_4": ""
    }
]